MANIFEST.in
README.md
setup.py
djdt_pev/__init__.py
djdt_pev.egg-info/PKG-INFO
djdt_pev.egg-info/SOURCES.txt
djdt_pev.egg-info/dependency_links.txt
djdt_pev.egg-info/requires.txt
djdt_pev.egg-info/top_level.txt
djdt_pev/panels/__init__.py
djdt_pev/panels/pev_sql.py
djdt_pev/static/pev_sql/css/styles.css
djdt_pev/static/pev_sql/fonts/FontAwesome.otf
djdt_pev/static/pev_sql/fonts/fontawesome-webfont.eot
djdt_pev/static/pev_sql/fonts/fontawesome-webfont.ttf
djdt_pev/static/pev_sql/fonts/fontawesome-webfont.woff
djdt_pev/static/pev_sql/fonts/fontawesome-webfont.woff2
djdt_pev/static/pev_sql/fonts/noto-sans-700.ttf
djdt_pev/static/pev_sql/fonts/noto-sans-700italic.ttf
djdt_pev/static/pev_sql/fonts/noto-sans-italic.ttf
djdt_pev/static/pev_sql/fonts/noto-sans-regular.ttf
djdt_pev/static/pev_sql/fonts/source-code-pro-300.ttf
djdt_pev/static/pev_sql/fonts/source-code-pro-500.ttf
djdt_pev/static/pev_sql/img/pev-logo.png
djdt_pev/static/pev_sql/js/app.js
djdt_pev/static/pev_sql/js/bootstrap.js
djdt_pev/static/pev_sql/js/polyfills.js
djdt_pev/static/pev_sql/js/shim.js
djdt_pev/static/pev_sql/js/styles.css
djdt_pev/static/pev_sql/js/styles.js
djdt_pev/static/pev_sql/js/vendor.js
djdt_pev/templates/pev_sql/pev.html
djdt_pev/templates/pev_sql/pev_wrapper.html
djdt_pev/templates/pev_sql/sql_panel.html