Metadata-Version: 1.0
Name: djdt-pev
Version: 0.0.1
Summary: Django Debug Toolbar SQL Panel, with PEV interface for inspecting query plans
Home-page: https://github.com/theY4Kman/djdt-pev
Author: Zach "theY4Kman" Kanzler
Author-email: they4kman@gmail.com
License: MIT
Platform: UNKNOWN
